manylog/__init__.py
manylog/connection.py
manylog/listener.py
manylog/messages.py
manylog/py.typed
manylog/worker/__init__.py
manylog/worker/logging.py
manylog/worker/progress.py
manylog/worker/setup.py
manylog-0.1.0.dist-info/LICENSE.md
manylog-0.1.0.dist-info/METADATA
manylog-0.1.0.dist-info/WHEEL
manylog-0.1.0.dist-info/top_level.txt
manylog-0.1.0.dist-info/RECORD
