Metadata-Version: 2.1
Name: manylog
Version: 0.1.0
Summary: Collect log messages and progress updates from multiple processes.
Author-email: Michael Ekstrand <mdekstrand@drexel.edu>
License: Copyright (c) 2023 Drexel University and contributors
Project-URL: Documentation, https://manylog.readthedocs.io/
Project-URL: GitHub, https://github.com/lenskit/manylog
Classifier: License :: OSI Approved :: MIT License
Classifier: Programming Language :: Python :: 3
Classifier: Programming Language :: Python :: 3.10
Classifier: Programming Language :: Python :: 3.11
Classifier: Programming Language :: Python :: 3.12
Classifier: Operating System :: OS Independent
Requires-Python: >=3.10
License-File: LICENSE.md
Requires-Dist: progress-api >=0.1.0a5
Requires-Dist: pyzmq
Requires-Dist: typing-extensions ~=4.11
Requires-Dist: msgpack ==1.*
Provides-Extra: dev
Requires-Dist: setuptools >=64 ; extra == 'dev'
Requires-Dist: setuptools-scm >=8 ; extra == 'dev'
Requires-Dist: wheel ; extra == 'dev'
Requires-Dist: build ==1.* ; extra == 'dev'
Requires-Dist: ruff >=0.2 ; extra == 'dev'
Requires-Dist: pyright ; extra == 'dev'
Requires-Dist: copier ==9.* ; extra == 'dev'
Requires-Dist: unbeheader ~=1.3 ; extra == 'dev'
Requires-Dist: ipython ; extra == 'dev'
Requires-Dist: pyproject2conda ; extra == 'dev'
Requires-Dist: sphinx-autobuild ; extra == 'dev'
Requires-Dist: msgpack-types ; extra == 'dev'
Provides-Extra: doc
Requires-Dist: sphinx >=4.2 ; extra == 'doc'
Requires-Dist: sphinxext-opengraph >=0.5 ; extra == 'doc'
Requires-Dist: furo ; extra == 'doc'
Provides-Extra: test
Requires-Dist: pytest >=7 ; extra == 'test'
Requires-Dist: pytest-cov >=2.12 ; extra == 'test'
Requires-Dist: coverage >=5 ; extra == 'test'
